LICENSE
README.md
setup.py
django_dnoticias_auth.egg-info/PKG-INFO
django_dnoticias_auth.egg-info/SOURCES.txt
django_dnoticias_auth.egg-info/dependency_links.txt
django_dnoticias_auth.egg-info/requires.txt
django_dnoticias_auth.egg-info/top_level.txt
dnoticias_auth/__init__.py
dnoticias_auth/apps.py
dnoticias_auth/backends.py
dnoticias_auth/context_processors.py
dnoticias_auth/cookies_consts.py
dnoticias_auth/exceptions.py
dnoticias_auth/forms.py
dnoticias_auth/middleware.py
dnoticias_auth/models.py
dnoticias_auth/redis.py
dnoticias_auth/session.py
dnoticias_auth/signals.py
dnoticias_auth/urls.py
dnoticias_auth/utils.py
dnoticias_auth/views.py
dnoticias_auth/migrations/0001_initial.py
dnoticias_auth/migrations/0002_alter_user_id.py
dnoticias_auth/migrations/0003_alter_user_id.py
dnoticias_auth/migrations/0004_alter_user_id.py
dnoticias_auth/migrations/0005_alter_user_id.py
dnoticias_auth/migrations/__init__.py
dnoticias_auth/templates/authentication/app-data.html
dnoticias_auth/templates/authentication/password-recovery.html
dnoticias_auth/templates/authentication/silent-check-sso.html
dnoticias_auth/templates/authentication/includes/auth.html
dnoticias_auth/templates/authentication/includes/keycloak.html
dnoticias_auth/templatetags/__init__.py
dnoticias_auth/templatetags/auth_utils.py