Metadata-Version: 2.1
Name: django-dnoticias-auth
Version: 1.3.12
Home-page: https://www.dnoticias.pt/
Author: Pedro Mendes
Author-email: pedro.trabalho.uma@gmail.com
Maintainer: Nelson Gonçalves
Maintainer-email: ngoncalves@dnoticias.pt
License: MIT
License-File: LICENSE
